MANIFEST.in
README
setup.cfg
setup.py
instrumental/__init__.py
instrumental/api.py
instrumental/constructs.py
instrumental/htmlreport.py
instrumental/importer.py
instrumental/instrument.py
instrumental/metadata.py
instrumental/monkey.py
instrumental/pragmas.py
instrumental/recorder.py
instrumental/reporting.py
instrumental/run.py
instrumental/storage.py
instrumental/summary.py
instrumental/tools.py
instrumental/util.py
instrumental/xmlreport.py
instrumental.egg-info/PKG-INFO
instrumental.egg-info/SOURCES.txt
instrumental.egg-info/dependency_links.txt
instrumental.egg-info/entry_points.txt
instrumental.egg-info/not-zip-safe
instrumental.egg-info/requires.txt
instrumental.egg-info/top_level.txt
instrumental/compat/__init__.py
instrumental/compat/py2.py
instrumental/compat/py3.py
instrumental/plugins/__init__.py
instrumental/plugins/nose/__init__.py
instrumental/plugins/nose/tag_test_cases.py
instrumental/resources/jquery-1.7.1.min.js
instrumental/resources/jquery-ui-1.8.17.custom.min.js
instrumental/resources/styles.css
instrumental/resources/ui-lightness/jquery-ui-1.8.17.custom.css
instrumental/resources/ui-lightness/images/ui-bg_diagonals-thick_18_b81900_40x40.png
instrumental/resources/ui-lightness/images/ui-bg_diagonals-thick_20_666666_40x40.png
instrumental/resources/ui-lightness/images/ui-bg_flat_10_000000_40x100.png
instrumental/resources/ui-lightness/images/ui-bg_glass_100_f6f6f6_1x400.png
instrumental/resources/ui-lightness/images/ui-bg_glass_100_fdf5ce_1x400.png
instrumental/resources/ui-lightness/images/ui-bg_glass_65_ffffff_1x400.png
instrumental/resources/ui-lightness/images/ui-bg_gloss-wave_35_f6a828_500x100.png
instrumental/resources/ui-lightness/images/ui-bg_highlight-soft_100_eeeeee_1x100.png
instrumental/resources/ui-lightness/images/ui-bg_highlight-soft_75_ffe45c_1x100.png
instrumental/resources/ui-lightness/images/ui-icons_222222_256x240.png
instrumental/resources/ui-lightness/images/ui-icons_228ef1_256x240.png
instrumental/resources/ui-lightness/images/ui-icons_ef8c08_256x240.png
instrumental/resources/ui-lightness/images/ui-icons_ffd27a_256x240.png
instrumental/resources/ui-lightness/images/ui-icons_ffffff_256x240.png
instrumental/samples/__init__.py
instrumental/samples/boolean.py
