Metadata-Version: 1.0
Name: instrumental
Version: 0.5.1
Summary: A condition/decision coverage tool for Python
Home-page: UNKNOWN
Author: Matthew J Desmarais
Author-email: matthew.desmarais@gmail.com
License: GPL
Keywords: ast condition decision coverage
Platform: UNKNOWN
